iracing_mcp_server/__init__.py
iracing_mcp_server/leaderboard.py
iracing_mcp_server/prompt.py
iracing_mcp_server/server.py
iracing_mcp_server-0.1.2.dist-info/METADATA
iracing_mcp_server-0.1.2.dist-info/WHEEL
iracing_mcp_server-0.1.2.dist-info/entry_points.txt
iracing_mcp_server-0.1.2.dist-info/licenses/LICENSE
iracing_mcp_server-0.1.2.dist-info/RECORD
