Metadata-Version: 2.4
Name: iracing-mcp-server
Version: 0.1.2
Summary: MCP server for iRacing
Project-URL: Homepage, https://github.com/ellettie/iracing-mcp-server
Project-URL: Repository, https://github.com/ellettie/iracing-mcp-server
Author: ellettie
License: MIT License
License-File: LICENSE
Keywords: mcp,mcp-server
Classifier: License :: OSI Approved :: MIT License
Classifier: Programming Language :: Python :: 3
Classifier: Programming Language :: Python :: 3.13
Requires-Python: >=3.13
Requires-Dist: mcp[cli]>=1.12.2
Requires-Dist: pyirsdk>=1.3.5
